LICENSE.txt
MANIFEST.in
README.txt
requirements.txt
setup.py
bin/ezmomi
ezmomi/__init__.py
ezmomi/cli.py
ezmomi/ezmomi.py
ezmomi/params.py
ezmomi/version.py
ezmomi.egg-info/PKG-INFO
ezmomi.egg-info/SOURCES.txt
ezmomi.egg-info/dependency_links.txt
ezmomi.egg-info/requires.txt
ezmomi.egg-info/top_level.txt
ezmomi/config/config.yml.example