Metadata-Version: 1.0
Name: ezmomi
Version: 6.0.1
Summary: VMware vSphere Command line tool
Home-page: https://github.com/snobear/ezmomi
Author: Jason Ashby
Author-email: jashby2@gmail.com
License: LICENSE.txt
Platform: UNKNOWN
